bloxflip_api/__init__.py
bloxflip_api/setup.py
bloxflipeasily-0.0.2.dist-info/METADATA
bloxflipeasily-0.0.2.dist-info/WHEEL
bloxflipeasily-0.0.2.dist-info/top_level.txt
bloxflipeasily-0.0.2.dist-info/RECORD
