Metadata-Version: 2.1
Name: bloxflipeasily
Version: 0.0.2
Summary: Made by Pytronomy on youtube
Home-page: UNKNOWN
Author: Pytronomy
License: UNKNOWN
Platform: UNKNOWN
Classifier: Programming Language :: Python :: 3
Classifier: License :: OSI Approved :: MIT License
Classifier: Operating System :: OS Independent
Requires-Python: >=3.6
